<?xml version="1.0" encoding="UTF-8"?><record_update>
    <sys_dictionary action="DELETE" element="u_miles_on_start" table="x_295413_yachtclub_u_return_protocol">
        <active>true</active>
        <array>false</array>
        <array_denormalized>false</array_denormalized>
        <attributes/>
        <audit>false</audit>
        <calculation><![CDATA[(function calculatedFieldValue(current) {

	// Add your code here
	return '';  // return the calculated value

})(current);]]></calculation>
        <choice/>
        <choice_field/>
        <choice_table/>
        <column_label>Miles on Start</column_label>
        <comments/>
        <create_roles/>
        <default_value/>
        <defaultsort/>
        <delete_roles/>
        <dependent/>
        <dependent_on_field/>
        <display>false</display>
        <dynamic_creation>false</dynamic_creation>
        <dynamic_creation_script/>
        <dynamic_default_value/>
        <dynamic_ref_qual/>
        <element>u_miles_on_start</element>
        <element_reference>false</element_reference>
        <foreign_database/>
        <function_definition/>
        <function_field>false</function_field>
        <internal_type display_value="Decimal">decimal</internal_type>
        <mandatory>true</mandatory>
        <max_length>20</max_length>
        <name>x_295413_yachtclub_u_return_protocol</name>
        <next_element/>
        <primary>false</primary>
        <read_only>false</read_only>
        <read_roles/>
        <reference/>
        <reference_cascade_rule/>
        <reference_floats>false</reference_floats>
        <reference_key/>
        <reference_qual/>
        <reference_qual_condition/>
        <reference_type/>
        <sizeclass/>
        <spell_check>false</spell_check>
        <staged>false</staged>
        <sys_class_name>sys_dictionary</sys_class_name>
        <sys_created_by>admin</sys_created_by>
        <sys_created_on>2021-02-01 09:41:22</sys_created_on>
        <sys_id>09d5c2fd07422010adadff1d7c1ed029</sys_id>
        <sys_mod_count>0</sys_mod_count>
        <sys_name>Miles on Start</sys_name>
        <sys_package display_value="Yacht Club" source="x_295413_yachtclub">94499bab07a86010b26bf2508c1ed038</sys_package>
        <sys_policy/>
        <sys_scope display_value="Yacht Club">94499bab07a86010b26bf2508c1ed038</sys_scope>
        <sys_update_name>sys_dictionary_x_295413_yachtclub_u_return_protocol_u_miles_on_start</sys_update_name>
        <sys_updated_by>admin</sys_updated_by>
        <sys_updated_on>2021-02-01 09:41:22</sys_updated_on>
        <table_reference>false</table_reference>
        <text_index>false</text_index>
        <unique>false</unique>
        <use_dependent_field>false</use_dependent_field>
        <use_dynamic_default>false</use_dynamic_default>
        <use_reference_qualifier>simple</use_reference_qualifier>
        <virtual>false</virtual>
        <widget/>
        <write_roles/>
        <xml_view>false</xml_view>
    </sys_dictionary>
<sys_update_version action="INSERT_OR_UPDATE">
        <action>DELETE</action>
        <application display_value="Yacht Club">94499bab07a86010b26bf2508c1ed038</application>
        <file_path/>
        <instance_id>5e528beadb224450b847ac44d496195d</instance_id>
        <instance_name>dev97950</instance_name>
        <name>sys_dictionary_x_295413_yachtclub_u_return_protocol_u_miles_on_start</name>
        <payload>&lt;?xml version="1.0" encoding="UTF-8"?&gt;&lt;record_update&gt;
    &lt;sys_dictionary action="INSERT_OR_UPDATE" element="u_miles_on_start" table="x_295413_yachtclub_u_return_protocol"&gt;
        &lt;active&gt;true&lt;/active&gt;
        &lt;array&gt;false&lt;/array&gt;
        &lt;array_denormalized&gt;false&lt;/array_denormalized&gt;
        &lt;attributes/&gt;
        &lt;audit&gt;false&lt;/audit&gt;
        &lt;calculation&gt;&lt;![CDATA[(function calculatedFieldValue(current) {

	// Add your code here
	return '';  // return the calculated value

})(current);]]&gt;&lt;/calculation&gt;
        &lt;choice/&gt;
        &lt;choice_field/&gt;
        &lt;choice_table/&gt;
        &lt;column_label&gt;Miles on Start&lt;/column_label&gt;
        &lt;comments/&gt;
        &lt;create_roles/&gt;
        &lt;default_value/&gt;
        &lt;defaultsort/&gt;
        &lt;delete_roles/&gt;
        &lt;dependent/&gt;
        &lt;dependent_on_field/&gt;
        &lt;display&gt;false&lt;/display&gt;
        &lt;dynamic_creation&gt;false&lt;/dynamic_creation&gt;
        &lt;dynamic_creation_script/&gt;
        &lt;dynamic_default_value/&gt;
        &lt;dynamic_ref_qual/&gt;
        &lt;element&gt;u_miles_on_start&lt;/element&gt;
        &lt;element_reference&gt;false&lt;/element_reference&gt;
        &lt;foreign_database/&gt;
        &lt;function_definition/&gt;
        &lt;function_field&gt;false&lt;/function_field&gt;
        &lt;internal_type display_value="Decimal"&gt;decimal&lt;/internal_type&gt;
        &lt;mandatory&gt;true&lt;/mandatory&gt;
        &lt;max_length&gt;20&lt;/max_length&gt;
        &lt;name&gt;x_295413_yachtclub_u_return_protocol&lt;/name&gt;
        &lt;next_element/&gt;
        &lt;primary&gt;false&lt;/primary&gt;
        &lt;read_only&gt;false&lt;/read_only&gt;
        &lt;read_roles/&gt;
        &lt;reference/&gt;
        &lt;reference_cascade_rule/&gt;
        &lt;reference_floats&gt;false&lt;/reference_floats&gt;
        &lt;reference_key/&gt;
        &lt;reference_qual/&gt;
        &lt;reference_qual_condition/&gt;
        &lt;reference_type/&gt;
        &lt;sizeclass/&gt;
        &lt;spell_check&gt;false&lt;/spell_check&gt;
        &lt;staged&gt;false&lt;/staged&gt;
        &lt;sys_class_name&gt;sys_dictionary&lt;/sys_class_name&gt;
        &lt;sys_created_by&gt;admin&lt;/sys_created_by&gt;
        &lt;sys_created_on&gt;2021-02-01 09:41:22&lt;/sys_created_on&gt;
        &lt;sys_id&gt;09d5c2fd07422010adadff1d7c1ed029&lt;/sys_id&gt;
        &lt;sys_mod_count&gt;0&lt;/sys_mod_count&gt;
        &lt;sys_name&gt;Miles on Start&lt;/sys_name&gt;
        &lt;sys_package display_value="Yacht Club" source="x_295413_yachtclub"&gt;94499bab07a86010b26bf2508c1ed038&lt;/sys_package&gt;
        &lt;sys_policy/&gt;
        &lt;sys_scope display_value="Yacht Club"&gt;94499bab07a86010b26bf2508c1ed038&lt;/sys_scope&gt;
        &lt;sys_update_name&gt;sys_dictionary_x_295413_yachtclub_u_return_protocol_u_miles_on_start&lt;/sys_update_name&gt;
        &lt;sys_updated_by&gt;admin&lt;/sys_updated_by&gt;
        &lt;sys_updated_on&gt;2021-02-01 09:41:22&lt;/sys_updated_on&gt;
        &lt;table_reference&gt;false&lt;/table_reference&gt;
        &lt;text_index&gt;false&lt;/text_index&gt;
        &lt;unique&gt;false&lt;/unique&gt;
        &lt;use_dependent_field&gt;false&lt;/use_dependent_field&gt;
        &lt;use_dynamic_default&gt;false&lt;/use_dynamic_default&gt;
        &lt;use_reference_qualifier&gt;simple&lt;/use_reference_qualifier&gt;
        &lt;virtual&gt;false&lt;/virtual&gt;
        &lt;widget/&gt;
        &lt;write_roles/&gt;
        &lt;xml_view&gt;false&lt;/xml_view&gt;
    &lt;/sys_dictionary&gt;
&lt;/record_update&gt;</payload>
        <payload_hash>-393228021</payload_hash>
        <record_name>Return Protocol.Miles on Start</record_name>
        <reverted_from/>
        <source>aace070f07222010adadff1d7c1ed0db</source>
        <source_table>sys_upgrade_history</source_table>
        <state>previous</state>
        <sys_created_by>admin</sys_created_by>
        <sys_created_on>2021-03-02 08:43:20</sys_created_on>
        <sys_id>b7de4b0f07222010adadff1d7c1ed0e0</sys_id>
        <sys_mod_count>0</sys_mod_count>
        <sys_recorded_at>177f21b23070000001</sys_recorded_at>
        <sys_updated_by>admin</sys_updated_by>
        <sys_updated_on>2021-03-02 08:43:20</sys_updated_on>
        <type>Dictionary</type>
        <update_guid>f3de4b0faf2220109a0e5f94bcbb53e0</update_guid>
        <update_guid_history>f3de4b0faf2220109a0e5f94bcbb53e0:0,b51a0b0bf92220101ae64aa704ed7f7e:-905737991,54a643ee465e20107d415bc6318b0b60:0,79434b2eba5e2010c7567b129f3ae227:-905737991,95133a19d7122410207facded431ae7f:0,784276d575122410c1e9bbc1ca9305f4:-905737991,200b72461ace2010256e792399067f18:0,cf6af2064fce2010ed42c3acbb7938e6:-905737991,26d83682cece20103e1d2b281f959ee0:0,e1d67602c3ce2010de4362d786f6bd53:-905737991,fe0eb8c2868a20103f5b3b482a7f7257:0,7cc5b08e824a2010987056374ca26785:-905737991,51572406434a20103c3b06177e27f173:0,31dd1c4e8f0a201040382d2f4ef3b828:-905737991,1a782bf9c4862010fcc2c0f22fc59706:0,3cf7ebb9dd862010f77e231ade5c5ace:-905737991,b0f4efb5c68620101a3fc0cd4fae67a8:0,cc3423b56b8620105cfaf45fde464d9f:-905737991,48a167f1498620104242d043b4de9159:0,cd612fb1988620108000d1625e889217:-905737991,239c0ff1b2462010bd3c9f96ca11229d:0,29d94b7100462010e1044475a06e0e98:-905737991,06d583bd0a0620109baeec105322b802:0,5e950b7d7f062010ad9a543156d35bea:-905737991,4b0646fd484220107c8338b60cbe7042:1242424621</update_guid_history>
    </sys_update_version>
    <sys_metadata_delete action="INSERT_OR_UPDATE">
        <sys_audit_delete/>
        <sys_class_name>sys_metadata_delete</sys_class_name>
        <sys_created_by>admin</sys_created_by>
        <sys_created_on>2021-03-02 08:51:02</sys_created_on>
        <sys_db_object display_value="" name="sys_dictionary">sys_dictionary</sys_db_object>
        <sys_id>4318dd8ed9094f5c87fbcbc84b35cb10</sys_id>
        <sys_metadata>d8de870f07222010adadff1d7c1ed04b</sys_metadata>
        <sys_mod_count>0</sys_mod_count>
        <sys_name>Miles on Start</sys_name>
        <sys_package display_value="Yacht Club" source="x_295413_yachtclub">94499bab07a86010b26bf2508c1ed038</sys_package>
        <sys_parent display_value="">50de870f07222010adadff1d7c1ed03f</sys_parent>
        <sys_policy/>
        <sys_scope display_value="Yacht Club">94499bab07a86010b26bf2508c1ed038</sys_scope>
        <sys_scope_delete display_value="">30da5e27c993460f93ff8ac00b66dfa1</sys_scope_delete>
        <sys_update_name>sys_dictionary_x_295413_yachtclub_u_return_protocol_u_miles_on_start</sys_update_name>
        <sys_update_version display_value="sys_dictionary_x_295413_yachtclub_u_return_protocol_u_miles_on_start">b7de4b0f07222010adadff1d7c1ed0e0</sys_update_version>
        <sys_updated_by>admin</sys_updated_by>
        <sys_updated_on>2021-03-02 08:51:02</sys_updated_on>
    </sys_metadata_delete>
</record_update>
